{
  "$schema": "https://raw.githubusercontent.com/devcontainers/spec/main/schemas/devContainer.schema.json",
  "name": "shokunin (Rust)",
  "image": "mcr.microsoft.com/devcontainers/rust:1-bookworm",
  "features": {
    "ghcr.io/devcontainers/features/git:1": {},
    "ghcr.io/devcontainers/features/github-cli:1": {}
  },
  "containerEnv": {
    "RUST_BACKTRACE": "1",
    "SSG_HOST": "0.0.0.0"
  },
  "forwardPorts": [3000, 8000],
  "portsAttributes": {
    "3000": { "label": "multilingual example", "onAutoForward": "notify" },
    "8000": { "label": "ssg --serve",          "onAutoForward": "notify" }
  },
  "postCreateCommand": "make init",
  "customizations": {
    "vscode": {
      "extensions": [
        "rust-lang.rust-analyzer",
        "tamasfe.even-better-toml",
        "vadimcn.vscode-lldb",
        "usernamehw.errorlens"
      ],
      "settings": {
        "editor.formatOnSave": true,
        "[rust]": { "editor.defaultFormatter": "rust-lang.rust-analyzer" },
        "rust-analyzer.check.command": "clippy"
      }
    }
  }
}
